teddynote/__init__.py
teddynote/dataset.py
teddynote/models.py
teddynote/utils.py
teddynote-0.2.1.dist-info/METADATA
teddynote-0.2.1.dist-info/WHEEL
teddynote-0.2.1.dist-info/top_level.txt
teddynote-0.2.1.dist-info/RECORD
