Metadata-Version: 2.1
Name: teddynote
Version: 0.2.1
Summary: datasets and tutorial package made and maintained by TeddyNote
Home-page: https://github.com/teddylee777/datasets
Author: teddylee777
Author-email: teddylee777@gmail.com
Keywords: teddynote,teddylee777,python datasets,python tutorial,machine learning,deep learning,optuna
Classifier: Programming Language :: Python :: 3
Classifier: Programming Language :: Python :: 3.2
Classifier: Programming Language :: Python :: 3.3
Classifier: Programming Language :: Python :: 3.4
Classifier: Programming Language :: Python :: 3.5
Classifier: Programming Language :: Python :: 3.6
Classifier: Programming Language :: Python :: 3.7
Classifier: Programming Language :: Python :: 3.8
Classifier: Programming Language :: Python :: 3.9
Requires-Python: >=3
Requires-Dist: tqdm
Requires-Dist: pandas
Requires-Dist: scikit-learn
Requires-Dist: lightgbm
Requires-Dist: xgboost
Requires-Dist: catboost
Requires-Dist: optuna
